MANIFEST.in
README.rst
setup.py
docs/HISTORY.txt
docs/LICENSE.GPL
docs/LICENSE.txt
simplelayout/__init__.py
simplelayout.ui.dragndrop.egg-info/PKG-INFO
simplelayout.ui.dragndrop.egg-info/SOURCES.txt
simplelayout.ui.dragndrop.egg-info/dependency_links.txt
simplelayout.ui.dragndrop.egg-info/entry_points.txt
simplelayout.ui.dragndrop.egg-info/namespace_packages.txt
simplelayout.ui.dragndrop.egg-info/not-zip-safe
simplelayout.ui.dragndrop.egg-info/requires.txt
simplelayout.ui.dragndrop.egg-info/top_level.txt
simplelayout/ui/__init__.py
simplelayout/ui/dragndrop/__init__.py
simplelayout/ui/dragndrop/config.py
simplelayout/ui/dragndrop/configure.zcml
simplelayout/ui/dragndrop/testing.py
simplelayout/ui/dragndrop/Extensions/__init__.py
simplelayout/ui/dragndrop/Extensions/install.py
simplelayout/ui/dragndrop/browser/__init__.py
simplelayout/ui/dragndrop/browser/configure.zcml
simplelayout/ui/dragndrop/browser/views.py
simplelayout/ui/dragndrop/browser/resources/interface.js
simplelayout/ui/dragndrop/browser/resources/jquery-ui-current.js
simplelayout/ui/dragndrop/browser/resources/sl-dnd-reorder.js
simplelayout/ui/dragndrop/browser/resources/sl-dnd-style.css
simplelayout/ui/dragndrop/profiles/default/cssregistry.xml
simplelayout/ui/dragndrop/profiles/default/jsregistry.xml
simplelayout/ui/dragndrop/profiles/default/metadata.xml
simplelayout/ui/dragndrop/profiles/uninstall/cssregistry.xml
simplelayout/ui/dragndrop/profiles/uninstall/jsregistry.xml
simplelayout/ui/dragndrop/tests/__init__.py
simplelayout/ui/dragndrop/tests/test_installation.py
simplelayout/ui/dragndrop/tests/test_uninstall.py