Metadata-Version: 1.1
Name: simplelayout.ui.dragndrop
Version: 3.1.0
Summary: simplelayout drag and drop support
Home-page: https://github.com/4teamwork/simplelayout.ui.dragndrop
Author: 4teamwork GmbH
Author-email: mailto:info@4teamwork.ch
License: GPL2
Platform: UNKNOWN
Classifier: Framework :: Plone
Classifier: Programming Language :: Python
Classifier: Topic :: Software Development :: Libraries :: Python Modules
